{
    "id": "cust0096",
    "password": "scrypt:32768:8:1$8GJu8UW4npJffcwl$3687a100ba07ed8e3023311d7b30540e81aeea4c9c8eefb31595db5bb7a633171ab853e80eacebaf2ce114ce45010aa0c48a89da7ae9730e9534b298e302872f",
    "personal_details": {
        "first_name": "Alice",
        "last_name": "Smith",
        "date_of_birth": "1958-07-20",
        "age": 67,
        "nationality": "Irish",
        "residency_status": "UK Resident",
        "address": {
            "street": "194 Queen Street",
            "city": "Bristol",
            "postcode": "CB3 9TD",
            "country": "UK"
        },
        "contact_details": {
            "email": "alice.smith@email.com",
            "phone": "+44 7985601432"
        },
        "kyc_status": {
            "identity_verified": true,
            "identity_documents": [
                {
                    "type": "Passport",
                    "expiry_date": "2030-11-30"
                },
                {
                    "type": "Driving Licence",
                    "date_issued": "2024-04-15"
                }
            ],
            "uk_resident": true
        }
    },
    "financial_profile": {
        "employment_status": "Retired",
        "employment_type": "Pension",
        "annual_income": 111657,
        "monthly_income": 9304.75,
        "monthly_expenses": 3933,
        "disposable_income": 5371.75,
        "debt_obligations": [
            {
                "type": "Car Loan",
                "monthly_payment": 420,
                "outstanding_balance": 27581
            },
            {
                "type": "Car Loan",
                "monthly_payment": 137,
                "outstanding_balance": 38713
            },
            {
                "type": "Personal Loan",
                "monthly_payment": 371,
                "outstanding_balance": 31953
            }
        ],
        "total_monthly_debt_payments": 928,
        "disposable_income_after_debts": 4443.75,
        "minimum_income_threshold_met": true,
        "open_banking_data": {
            "account_balance": 110561,
            "average_monthly_spending": 2662,
            "average_monthly_saving": 2149.04,
            "spending_patterns": [
                {
                    "category": "Groceries",
                    "amount": 1160
                },
                {
                    "category": "Rent",
                    "amount": 727
                },
                {
                    "category": "Utilities",
                    "amount": 164
                },
                {
                    "category": "Entertainment",
                    "amount": 611
                }
            ],
            "saving_habits": "Irregular",
            "insufficient_saving_habits_flag": false,
            "unutilized_disposable_income": 2294.71
        }
    },
    "risk_profile": {
        "risk_tolerance": "Low",
        "risk_score": 2,
        "investment_experience": "Significant",
        "product_alignment": true,
        "behavioral_indicators": {
            "previous_product_preferences": [
                "Stocks and Shares ISA"
            ],
            "savings_patterns": "Lump sum"
        }
    },
    "financial_goals": {
        "goal_type": "Retirement Income",
        "timeline": "Short-term",
        "desired_retirement_age": 68,
        "expected_retirement_income": 33779,
        "contribution_flexibility": "Low",
        "goal_details": {
            "target_amount": 415415,
            "current_progress": 642024
        }
    },
    "product_eligibility": {
        "age_eligibility_met": true,
        "employment_type_eligibility": true,
        "minimum_investment_met": true,
        "pension_status": "Personal Pension Plan",
        "already_enrolled_in_nest": true
    },
    "regulatory_compliance": {
        "fca_suitability_assessment": true,
        "mifid_ii_compliance": true,
        "aml_checks_passed": true,
        "fatca_crs_status": "Applicable",
        "marketing_opt_in": false
    },
    "cognitive_digital_accessibility": {
        "digital_savviness": "Low",
        "advisory_support_needed": true,
        "communication_preferences": [
            "Online Chat",
            "Mail",
            "Mobile App",
            "Video Conferencing",
            "Phone"
        ]
    },
    "product_offerings": {
        "existing_products": [
            "General Investment Account",
            "Lifetime ISA"
        ],
        "product_duplication_check": true,
        "bundle_offers_eligible": [
            "Income Protection Insurance"
        ],
        "promotions_eligible": false
    },
    "tax_efficiency": {
        "active_isas": [],
        "isa_limit_exceeded": false,
        "pension_contribution_limits": {
            "annual_allowance_remaining": 32219,
            "lifetime_allowance_remaining": 457837
        },
        "lisa_eligibility": false
    }
}